amplify_bench/__init__.py
amplify_bench/downloader.py
amplify_bench/job.py
amplify_bench/result.py
amplify_bench/runner.py
amplify_bench/timer.py
amplify_bench/util.py
amplify_bench/cli/__init__.py
amplify_bench/cli/cli.py
amplify_bench/cli/download_all.py
amplify_bench/cli/parser.py
amplify_bench/cli/run.py
amplify_bench/cli/stats.py
amplify_bench/cli/schemas/annealing_benchmark_json_schema.yml
amplify_bench/cli/schemas/benchmark.json
amplify_bench/cli/schemas/index.html
amplify_bench/cli/schemas/report_data.json
amplify_bench/cli/schemas/result.json
amplify_bench/client_config/__init__.py
amplify_bench/client_config/base.py
amplify_bench/client_config/dwave.py
amplify_bench/client_config/fixstars.py
amplify_bench/client_config/fujitsu.py
amplify_bench/client_config/gurobi.py
amplify_bench/client_config/nec.py
amplify_bench/client_config/toshiba.py
amplify_bench/client_config/toshiba_sqbm2.py
amplify_bench/problem/__init__.py
amplify_bench/problem/base.py
amplify_bench/problem/cvrp.py
amplify_bench/problem/maxcut.py
amplify_bench/problem/qap.py
amplify_bench/problem/qplib.py
amplify_bench/problem/sudoku.py
amplify_bench/problem/tsp.py
amplify_bench/problem/data/README.md
amplify_bench/problem/data/CVRPLIB/instance_list.txt
amplify_bench/problem/data/GSET/best_solutions.csv
amplify_bench/problem/data/GSET/instance_list.txt
amplify_bench/problem/data/QAPLIB/esc32a.sln
amplify_bench/problem/data/QAPLIB/esc32b.sln
amplify_bench/problem/data/QAPLIB/esc32c.sln
amplify_bench/problem/data/QAPLIB/esc32d.sln
amplify_bench/problem/data/QAPLIB/instance_list.txt
amplify_bench/problem/data/QPLIB/best_solutions.csv
amplify_bench/problem/data/QPLIB/instance_list.txt
amplify_bench/problem/data/SUDOKULIB/16x16_1_000
amplify_bench/problem/data/SUDOKULIB/16x16_easy_233
amplify_bench/problem/data/SUDOKULIB/16x16_hard_194
amplify_bench/problem/data/SUDOKULIB/25x25_000
amplify_bench/problem/data/SUDOKULIB/9x9_h17_055
amplify_bench/problem/data/SUDOKULIB/9x9_h39_022
amplify_bench-0.2.0.dist-info/LICENSE
amplify_bench-0.2.0.dist-info/METADATA
amplify_bench-0.2.0.dist-info/WHEEL
amplify_bench-0.2.0.dist-info/entry_points.txt
amplify_bench-0.2.0.dist-info/top_level.txt
amplify_bench-0.2.0.dist-info/RECORD
