Metadata-Version: 2.1
Name: amplify-bench
Version: 0.2.0
Summary: Benchmark framework for Quantum and Classical Annealing Machines
Home-page: https://github.com/fixstars/amplify-benchmark
Author: Fixstars Corporation, Fixstars Amplify Corporation
Author-email: "Yoshiki Matsuda" <y_matsuda@fixstars.com>
Maintainer: Yoshiki Matsuda, Hiroki Kawahara, Kosuke Suzuki
Keywords: quantum,quantum annealing,annealer,annealing machine,QUBO,quadratic unconstrained binary optimization,d-wave,digital annealer,sdk,sbm,simulated bifurcation,simulated annealing,Ising machine,Ising model,fixstars
Classifier: Environment :: Console
Classifier: Development Status :: 4 - Beta
Classifier: Intended Audience :: Developers
Classifier: Intended Audience :: Science/Research
Classifier: Topic :: Software Development :: Libraries :: Python Modules
Classifier: Topic :: Scientific/Engineering
Classifier: License :: OSI Approved :: MIT License
Classifier: Operating System :: POSIX :: Linux
Classifier: Operating System :: Microsoft :: Windows
Classifier: Operating System :: MacOS :: MacOS X
Classifier: Programming Language :: Python :: 3.8
Classifier: Programming Language :: Python :: 3.9
Classifier: Programming Language :: Python :: 3.10
Classifier: Programming Language :: Python :: 3.11
Requires-Python: >=3.8
License-File: LICENSE
Requires-Dist: amplify[extra] <1.0.0
Requires-Dist: matplotlib
Requires-Dist: numpy
Requires-Dist: pandas
Requires-Dist: boto3
Requires-Dist: tsplib95
Requires-Dist: vrplib
Requires-Dist: tqdm
Requires-Dist: jsonschema
Requires-Dist: click !=8.1.4,!=8.1.5
Requires-Dist: python-dotenv
Requires-Dist: pyyaml
Requires-Dist: mypy-boto3-s3
Requires-Dist: requests
